{
  "schemaVersion": 1,
  "id": "lightningmod",
  "version": "${version}",
  "name": "lightningmod",
  "description": "A mod that increases the number of lightning strikes during thunderstorms.",
  "authors": [
    "p4pingvin4ik"
  ],

  "license": "MIT",
  "icon": "assets/lightningmod/icon.png",
  "environment": "*",
  "entrypoints": {
    "main": [
      "net.p4pingvin4ik.lightningmod.LightningMod"
    ],
    "modmenu": [
      "net.p4pingvin4ik.lightningmod.LightningModMenuIntegration"
    ]
  },
  "mixins": [
    {
      "config": "lightningmod.mixins.json",
      "environment": "*"
    }
  ],
  "depends": {
    "minecraft": "~26.2",
    "java": ">=25",
    "fabricloader": ">=${loader_version}",
    "fabric-api": "*",
    "yet_another_config_lib_v3": "*"
  }
}
